{
  "sku": "130-001-10041",
  "type": "protections",
  "subtype": "dress",
  "name": "Drop Dress, Modified (ModDD-14)",
  "mfr": "",
  "cost": 144000,
  "mass": 108,
  "techLevel": 14,
  "qrebs": "N/A",
  "image": "",
  "description": "<p><!-- Summary Start -->Drop dress is structured to protect against the extreme temperatures of orbital reentry.<!-- Summary End --></p>",
  "accessories": [],
  "categories": ["protections", "dress"],
  "sources": [
    {
      "publication": "Traveller 5.10 Core Rules Book 1 : Characters and Combat",
      "authors": ["Miller, Marc"],
      "publisher": {
        "name": "Far Future Enterprises",
        "url": "https://www.farfuture.net"
      }
    }
  ],
  "tags": ["products", "protections", "dress"]
}
