{
  "sku": "130-002-10039",
  "type": "protections",
  "subtype": "suits",
  "name": "Battle Suit, Oversize (OsBS-9)",
  "cost": 50000,
  "mass": 200,
  "techLevel": 9,
  "qrebs": "N/A",
  "image": "",
  "description": "<p><!-- Summary Start -->Battle suits incorporate protections against most dangers, attacks, and threats on the battlefield.<!-- Summary End --></p>",
  "accessories": [],
  "categories": ["protections", "suits"],
  "sources": [
    {
      "publication": "Traveller 5.10 Core Rules Book 1 : Characters and Combat",
      "authors": ["Miller, Marc W."],
      "publisher": "Far Future Enterprises"
    }
  ],
  "tags": ["products", "protections", "suits"]
}
